slurm_rest_client/__init__.py
slurm_rest_client/api/__init__.py
slurm_rest_client/api/openapi/__init__.py
slurm_rest_client/api/openapi/openapi.py
slurm_rest_client/api/openapi/openapi_v3_get.py
slurm_rest_client/api/openapi/openapijson.py
slurm_rest_client/api/openapi/openapiyaml.py
slurm_rest_client/api/slurm/__init__.py
slurm_rest_client/api/slurm/slurm_v0040_delete_job.py
slurm_rest_client/api/slurm/slurm_v0040_delete_jobs.py
slurm_rest_client/api/slurm/slurm_v0040_delete_node.py
slurm_rest_client/api/slurm/slurm_v0040_get_diag.py
slurm_rest_client/api/slurm/slurm_v0040_get_job.py
slurm_rest_client/api/slurm/slurm_v0040_get_jobs.py
slurm_rest_client/api/slurm/slurm_v0040_get_jobs_state.py
slurm_rest_client/api/slurm/slurm_v0040_get_licenses.py
slurm_rest_client/api/slurm/slurm_v0040_get_node.py
slurm_rest_client/api/slurm/slurm_v0040_get_nodes.py
slurm_rest_client/api/slurm/slurm_v0040_get_partition.py
slurm_rest_client/api/slurm/slurm_v0040_get_partitions.py
slurm_rest_client/api/slurm/slurm_v0040_get_ping.py
slurm_rest_client/api/slurm/slurm_v0040_get_reconfigure.py
slurm_rest_client/api/slurm/slurm_v0040_get_reservation.py
slurm_rest_client/api/slurm/slurm_v0040_get_reservations.py
slurm_rest_client/api/slurm/slurm_v0040_get_shares.py
slurm_rest_client/api/slurm/slurm_v0040_post_job.py
slurm_rest_client/api/slurm/slurm_v0040_post_job_submit.py
slurm_rest_client/api/slurm/slurm_v0040_post_node.py
slurm_rest_client/api/slurmdb/__init__.py
slurm_rest_client/api/slurmdb/slurmdb_v0040_delete_account.py
slurm_rest_client/api/slurmdb/slurmdb_v0040_delete_association.py
slurm_rest_client/api/slurmdb/slurmdb_v0040_delete_associations.py
slurm_rest_client/api/slurmdb/slurmdb_v0040_delete_cluster.py
slurm_rest_client/api/slurmdb/slurmdb_v0040_delete_single_qos.py
slurm_rest_client/api/slurmdb/slurmdb_v0040_delete_user.py
slurm_rest_client/api/slurmdb/slurmdb_v0040_delete_wckey.py
slurm_rest_client/api/slurmdb/slurmdb_v0040_get_account.py
slurm_rest_client-0.1.4.dist-info/METADATA
slurm_rest_client-0.1.4.dist-info/WHEEL
slurm_rest_client-0.1.4.dist-info/RECORD
